rt_thread_studio/__init__.py
rt_thread_studio/bsp_checker.py
rt_thread_studio/bsp_parser.py
rt_thread_studio/rt_thread_studio_tools.py
rt_thread_studio/board_support_package_generator/__init__.py
rt_thread_studio/board_support_package_generator/bsp_generator/__init__.py
rt_thread_studio/board_support_package_generator/bsp_generator/board.py
rt_thread_studio/board_support_package_generator/bsp_generator/bsp_descriptor.py
rt_thread_studio/board_support_package_generator/bsp_generator/builtin_files.py
rt_thread_studio/board_support_package_generator/bsp_generator/chip.py
rt_thread_studio/board_support_package_generator/bsp_generator/external_files.py
rt_thread_studio/board_support_package_generator/bsp_generator/generate.py
rt_thread_studio/board_support_package_generator/bsp_generator/project.py
rt_thread_studio/board_support_package_generator/bsp_generator/temp_yaml.py
rt_thread_studio/board_support_package_generator/config/__init__.py
rt_thread_studio/board_support_package_generator/config/config.py
rt_thread_studio/board_support_package_generator/template/debug/svd/STM32L4x5.svd
rt_thread_studio/board_support_package_generator/template/documents/images/board_large.png
rt_thread_studio/board_support_package_generator/template/documents/images/board_small.png
rt_thread_studio/board_support_package_generator/template/documents/manuals/UM3004-RT-Thread-IoT Board.pdf
rt_thread_studio/board_support_package_generator/template/documents/sheet/STM32L475xx Datasheet.pdf
rt_thread_studio-2.4.dist-info/METADATA
rt_thread_studio-2.4.dist-info/WHEEL
rt_thread_studio-2.4.dist-info/entry_points.txt
rt_thread_studio-2.4.dist-info/top_level.txt
rt_thread_studio-2.4.dist-info/RECORD
