Metadata-Version: 2.1
Name: rt-thread-studio
Version: 2.4
Summary: Tools for RT-Thread Studio
Home-page: https://www.python.org/sigs/distutils-sig/
Author: RealThread
Author-email: chenyaxing@rt-thread.com
License: UNKNOWN
Platform: UNKNOWN
Requires-Dist: PyYAML (>=5.3.1)
Requires-Dist: click (>=7.1.1)
